README.rst
setup.py
lumberjill/__init__.py
lumberjill/emailclients.py
lumberjill/filters.py
lumberjill/handlers.py
lumberjill.egg-info/PKG-INFO
lumberjill.egg-info/SOURCES.txt
lumberjill.egg-info/dependency_links.txt
lumberjill.egg-info/top_level.txt