Metadata-Version: 1.1
Name: lumberjill
Version: 0.1
Summary: Provides additional logging filters and handlers.
Home-page: http://github.com/firstopinion/lumberjill
Author: Topher Fisher
Author-email: topher@firstopinionapp.com
License: MIT
Platform: UNKNOWN
Classifier: Development Status :: 4 - Beta
Classifier: Environment :: Web Environment
Classifier: Intended Audience :: Developers
Classifier: License :: OSI Approved :: MIT License
Classifier: Operating System :: OS Independent
Classifier: Topic :: Database
Classifier: Topic :: Software Development :: Libraries
Classifier: Topic :: Utilities
Classifier: Programming Language :: Python :: 2.7
